infrahub/cli.py
infrahub-0.1.2.dist-info/METADATA
infrahub-0.1.2.dist-info/WHEEL
infrahub-0.1.2.dist-info/entry_points.txt
infrahub-0.1.2.dist-info/RECORD
