Metadata-Version: 2.1
Name: infrahub
Version: 0.1.2
Summary: Infrahub by OpsMill
Home-page: https://opsmill.com
Author: OpsMill
Author-email: info@opsmill.com
Requires-Python: >=3.9,<3.13
Classifier: Intended Audience :: Developers
Classifier: Programming Language :: Python :: 3
Classifier: Programming Language :: Python :: 3.9
Classifier: Programming Language :: Python :: 3.10
Classifier: Programming Language :: Python :: 3.11
Classifier: Programming Language :: Python :: 3.12
Project-URL: Documentation, https://docs.infrahub.app/
Project-URL: Repository, https://github.com/opsmill/infrahub
